README
setup.py
gerrit/__init__.py
gerrit/db.py
gerrit/decode.py
gerrit/error.py
gerrit/model.py
gerrit/raw.py
gerrit/rpc.py
gerrit/service.py
gerrit/util.py
gerrit.egg-info/PKG-INFO
gerrit.egg-info/SOURCES.txt
gerrit.egg-info/dependency_links.txt
gerrit.egg-info/requires.txt
gerrit.egg-info/top_level.txt