Metadata-Version: 1.0
Name: gerrit
Version: 0.0.1
Summary: Client library for interacting with the Gerrit JSONRPC API
Home-page: https://github.com/bcwaldon/python-gerrit
Author: Brian Waldon
Author-email: bcwaldon@gmail.com
License: UNKNOWN
Platform: UNKNOWN
